LICENSE
MANIFEST.in
README.md
pyproject.toml
setup.py
docs/Makefile
docs/generate_api_docs.py
docs/make.bat
docs/requirements-docs.txt
docs/source/changelog.md
docs/source/command_line.rst
docs/source/conf.py
docs/source/contributing_guide.md
docs/source/faq.rst
docs/source/index.rst
docs/source/installation.rst
docs/source/introduction.rst
docs/source/legacy.rst
docs/source/theory.rst
docs/source/tutorials.rst
docs/source/advanced/lammps.rst
docs/source/apidoc/kliff.analyzers.rst
docs/source/apidoc/kliff.atomic_data.rst
docs/source/apidoc/kliff.calculators.rst
docs/source/apidoc/kliff.dataset.rst
docs/source/apidoc/kliff.descriptors.rst
docs/source/apidoc/kliff.error.rst
docs/source/apidoc/kliff.log.rst
docs/source/apidoc/kliff.loss.rst
docs/source/apidoc/kliff.models.rst
docs/source/apidoc/kliff.neighbor.rst
docs/source/apidoc/kliff.nn.rst
docs/source/apidoc/kliff.parallel.rst
docs/source/apidoc/kliff.rst
docs/source/apidoc/kliff.uq.rst
docs/source/apidoc/kliff.utils.rst
docs/source/howto/howto.rst
docs/source/howto/install_kim_model.rst
docs/source/howto/new_model.rst
docs/source/howto/parallelize.rst
docs/source/howto/save_load_model.rst
docs/source/img/bootstrap.png
docs/source/img/logo.jpg
docs/source/img/uq_cartoon.png
docs/source/introduction/ConfigurationTransforms.ipynb
docs/source/introduction/Dataset.ipynb
docs/source/introduction/Trainer_and_kim.ipynb
docs/source/introduction/Trainer_dnn.ipynb
docs/source/introduction/Trainer_gnn.ipynb
docs/source/modules/calculators.rst
docs/source/modules/dataset.rst
docs/source/modules/descriptors.rst
docs/source/modules/loss.rst
docs/source/modules/models.rst
docs/source/modules/modules.rst
docs/source/modules/uq.rst
docs/source/tutorials/kim_SW_Si.ipynb
docs/source/tutorials/lennard_jones.ipynb
docs/source/tutorials/linear_regression.ipynb
docs/source/tutorials/nn_Si.ipynb
docs/source/tutorials/nn_SiC.ipynb
docs/source/tutorials/parameter_transform.ipynb
docs/source/tutorials/uq_bootstrap.ipynb
kliff.egg-info/PKG-INFO
kliff.egg-info/SOURCES.txt
kliff.egg-info/dependency_links.txt
kliff.egg-info/entry_points.txt
kliff.egg-info/not-zip-safe
kliff.egg-info/requires.txt
kliff.egg-info/top_level.txt
