Metadata-Version: 2.4
Name: kliff
Version: 1.0.0
Summary: KLIFF: KIM-based Learning-Integrated Fitting Framework
Home-page: https://github.com/openkim/kliff
Author: Mingjian Wen
Author-email: wenxx151@gmail.com
Classifier: License :: OSI Approved :: GNU Lesser General Public License v2 (LGPLv2)
Classifier: Operating System :: OS Independent
License-File: LICENSE
Requires-Dist: requests
Requires-Dist: scipy
Requires-Dist: pyyaml
Requires-Dist: monty
Requires-Dist: loguru
Requires-Dist: ase<3.23
Requires-Dist: numpy<2.0
Provides-Extra: test
Requires-Dist: pytest; extra == "test"
Requires-Dist: pytest-cov; extra == "test"
Requires-Dist: kimpy; extra == "test"
Requires-Dist: emcee; extra == "test"
Requires-Dist: numpy<2.0; extra == "test"
Requires-Dist: ase<3.23; extra == "test"
Requires-Dist: libdescriptor; extra == "test"
Provides-Extra: torch
Requires-Dist: torch; extra == "torch"
Requires-Dist: torch_geometric; extra == "torch"
Requires-Dist: pytorch_lightning; extra == "torch"
Requires-Dist: torch_scatter; extra == "torch"
Requires-Dist: tensorboard; extra == "torch"
Requires-Dist: tensorboardx; extra == "torch"
Provides-Extra: docs
Requires-Dist: sphinx; extra == "docs"
Requires-Dist: furo; extra == "docs"
Requires-Dist: myst-nb; extra == "docs"
Requires-Dist: sphinx-autodoc-typehints; extra == "docs"
Requires-Dist: sphinx-copybutton; extra == "docs"
Requires-Dist: matplotlib; extra == "docs"
Dynamic: author
Dynamic: author-email
Dynamic: classifier
Dynamic: description
Dynamic: description-content-type
Dynamic: home-page
Dynamic: license-file
Dynamic: provides-extra
Dynamic: requires-dist
Dynamic: summary
